textraer/__init__.py
textraer/test.py
textraer/textraer.py
textraer-0.1.0.dist-info/LICENSE
textraer-0.1.0.dist-info/METADATA
textraer-0.1.0.dist-info/WHEEL
textraer-0.1.0.dist-info/top_level.txt
textraer-0.1.0.dist-info/RECORD
