Metadata-Version: 2.1
Name: textraer
Version: 0.1.0
Summary: Text processor with classification using DataBERT.
Home-page: https://github.com/avsolatorio/data-use/tree/main/scripts/DataBERT
Author: James Liounis
Author-email: liounisjames@gmail.com
License: MIT
Requires-Python: >=3.6
License-File: LICENSE
Requires-Dist: torch
Requires-Dist: transformers
Requires-Dist: numpy
Requires-Dist: scikit-learn
Requires-Dist: huggingface-hub
Requires-Dist: nltk
Requires-Dist: PyPDF2
Requires-Dist: requests
